netexplorer/__init__.py
netexplorer/crawler.py
netexplorer/sitesMap.py
netexplorer/utils/__init__.py
netexplorer/utils/database.py
netexplorer/utils/url.py
netexplorer-2.0.4.dist-info/METADATA
netexplorer-2.0.4.dist-info/WHEEL
netexplorer-2.0.4.dist-info/top_level.txt
netexplorer-2.0.4.dist-info/RECORD
