Metadata-Version: 2.2
Name: netexplorer
Version: 2.0.4
Summary: Web analysis tool
Author-email: Julien de Montmollin <jdm@futureofthe.tech>
Project-URL: Homepage, https://github.com/judemont/netexplorer
Project-URL: Issues, https://github.com/judemont/netexplorer/issues
Classifier: Programming Language :: Python :: 3
Classifier: Operating System :: OS Independent
Requires-Python: >=3.8
